clamp/__init__.py
clamp/cli.py
clamp/client.py
clamp/exceptions.py
clamp/models.py
clamp/storage.py
clamp/vector_ops.py
clamp_rag-1.2.0.dist-info/METADATA
clamp_rag-1.2.0.dist-info/WHEEL
clamp_rag-1.2.0.dist-info/entry_points.txt
clamp_rag-1.2.0.dist-info/licenses/LICENSE
clamp_rag-1.2.0.dist-info/RECORD
