Metadata-Version: 2.4
Name: clamp-rag
Version: 1.2.0
Summary: Git-like version control for RAG vector databases
License: MIT
License-File: LICENSE
Keywords: rag,vector-database,qdrant,version-control,llm
Author: Clamp Team
Requires-Python: >=3.10,<3.14
Classifier: Development Status :: 4 - Beta
Classifier: Intended Audience :: Developers
Classifier: License :: OSI Approved :: MIT License
Classifier: Programming Language :: Python :: 3
Classifier: Programming Language :: Python :: 3.10
Classifier: Programming Language :: Python :: 3.11
Classifier: Programming Language :: Python :: 3.12
Classifier: Programming Language :: Python :: 3.13
Classifier: Topic :: Scientific/Engineering :: Artificial Intelligence
Classifier: Topic :: Software Development :: Libraries :: Python Modules
Requires-Dist: click (>=8.1.7,<9.0.0)
Requires-Dist: httpx (>=0.27.0,<0.28.0)
Requires-Dist: qdrant-client (>=1.7.0,<2.0.0)
Requires-Dist: typer[all] (>=0.9.0,<0.10.0)
Project-URL: Homepage, https://github.com/athaapa/clamp-monorepo
Project-URL: Repository, https://github.com/athaapa/clamp-monorepo
